cleancat/__init__.py
cleancat/base.py
cleancat/mongo.py
cleancat/sqla.py
cleancat/utils.py
cleancat-1.0.0.dist-info/LICENSE
cleancat-1.0.0.dist-info/METADATA
cleancat-1.0.0.dist-info/WHEEL
cleancat-1.0.0.dist-info/top_level.txt
cleancat-1.0.0.dist-info/RECORD
