Metadata-Version: 2.1
Name: cleancat
Version: 1.0.0
Summary: Validation library for Python designed to be used with JSON REST frameworks
Home-page: http://github.com/elasticsales/cleancat
Author: Thomas Steinacher
Author-email: engineering@close.io
Maintainer: Thomas Steinacher
Maintainer-email: engineering@close.io
License: MIT
Platform: any
Classifier: Environment :: Web Environment
Classifier: Intended Audience :: Developers
Classifier: License :: OSI Approved :: MIT License
Classifier: Operating System :: OS Independent
Classifier: Programming Language :: Python
Classifier: Programming Language :: Python :: 3
Classifier: Programming Language :: Python :: 3.5
Classifier: Programming Language :: Python :: 3.6
Classifier: Programming Language :: Python :: 3.7
Classifier: Topic :: Internet :: WWW/HTTP :: Dynamic Content
Classifier: Topic :: Software Development :: Libraries :: Python Modules
Requires-Dist: python-dateutil
Requires-Dist: pytz
Provides-Extra: test
Requires-Dist: python-dateutil ; extra == 'test'
Requires-Dist: pytz ; extra == 'test'
Requires-Dist: pytest ; extra == 'test'
Requires-Dist: coverage ; extra == 'test'
Requires-Dist: mongoengine ; extra == 'test'
Requires-Dist: sqlalchemy ; extra == 'test'
